Workbook

Sheet Cover_Version
G2: MODEL: NVIDIA × Arm Acquisition Case Study (2026)
K9: Author: Akash Ghosal
K10: Model Type: M&A + Strategic Valuation + Regulatory Risk
K11: Version: 1.0
K12: Last Updated: 05.12.25
I16: Model Structure Overview
I18: Assumptions
I19: Raw Financials: NVIDIA
I20: Raw Financials: Arm
I21: DCF (Arm Standalone)
I22: DCF (Bull Case)
I23: DCF(Bear Case)
I24: Sensitivity & Scenario Analysis
I25: Charts

Sheet Assumptions
A1: Revenue Growth Assumptions (%)
A2: Year | B2: Base | C2: Bull | D2: Bear
A3: FY2026E | B3: 0.2 | C3: 0.25 | D3: 0.15
A4: FY2027E | B4: 0.18 | C4: 0.23 | D4: 0.12
A5: FY2028E | B5: 0.16 | C5: 0.2 | D5: 0.1
A6: FY2029E | B6: 0.14 | C6: 0.18 | D6: 0.08
A7: FY2030E | B7: 0.12 | C7: 0.16 | D7: 0.07
A9: Revenue Forecast (USD millions)
A10: (FY2025 Actual = 4,007)
A11: Year | B11: Base Case | C11: Bull Case | D11: Bear Case
A12: FY2025A | B12: 4007 | C12: 4007 | D12: 4007
A13: FY2026E | B13: 4808 | C13: 5009 | D13: 4608
A14: FY2027E | B14: 5673 | C14: 6160 | D14: 5161
A15: FY2028E | B15: 6579 | C15: 7392 | D15: 5677
A16: FY2029E | B16: 7505 | C16: 8714 | D16: 6130
A17: FY2030E | B17: 8405 | C17: 10104 | D17: 6560
A19: Margin Assumptions (as % of revenue)
A20: Item | B20: FY2026E | C20: FY2027E | D20: FY2028E | E20: FY2029E | F20: FY2030E
A21: Cost of Sales | B21: 0.03 | C21: 0.03 | D21: 0.03 | E21: 0.03 | F21: 0.03
A22: R&D | B22: 0.51 | C22: 0.5 | D22: 0.48 | E22: 0.47 | F22: 0.46
A23: SG&A | B23: 0.24 | C23: 0.23 | D23: 0.22 | E23: 0.21 | F23: 0.2
A26: Operating Assumptions
A27: Item | B27: % of Revenue
A28: Depreciation | B28: 0.03
A29: CapEx | B29: 0.025
A30: Change in Working Capital | B30: 0.01
A33: Discounting Assumptions
A34: Item | B34: Value
A35: WACC | B35: 0.1
A36: Terminal Growth (g) | B36: 0.03
A38: Sources Used for Forecasting
A39: ARM future revenue growth expected at ~18–22% annually according to analyst consensus (SimplyWallSt, Arm — Future Growth).
A40: ARM Q2 FY2026 earnings: +34% YoY revenue; +56% licensing, +21% royalty growth (Futurum Group).
A41: Analysts forecast sales rising from ~$4.0B (FY2025) to ~$5.9B by 2027 (MarketScreener).
A42: Long-term royalty TAM growth estimated 15–20% CAGR (ARM F-1 Prospectus).

Sheet RawFin_NVIDIA
A1: INCOME STATEMENT
A2: USD millions | B2: FY2022 | C2: FY2023 | D2: FY2024 | E2: FY2025
A3: Revenue | B3: 26914 | C3: 26974 | D3: 60922 | E3: 130497
A4: Cost of revenue | B4: 9439 | C4: 11618 | D4: 16621 | E4: 32639
A5: Gross Profit | B5: 17475 | C5: 15356 | D5: 44301 | E5: 97858
A6: Operating Exp | B6: 7434 | C6: 11312 | D6: 11329 | E6: 16405
A7: EBIT | B7: 10041 | C7: 4224 | D7: 32972 | E7: 81453
A8: Net Income | B8: 9752 | C8: 4368 | D8: 29760 | E8: 72800
A10: BALANCE SHEET
A11: USD millions | B11: FY2022 | C11: FY2023 | D11: FY2024 | E11: FY2025
A12: Cash | B12: 1990 | C12: 3389 | D12: 7280 | E12: 8589
A13: Total Assets | B13: 41182 | C13: 65728 | D13: 65728 | E13: 111601
A14: Total Liabilities | B14: 19081 | C14: 22750 | D14: 22750 | E14: 32274
A15: Total Equity | B15: 22101 | C15: 42978 | D15: 42978 | E15: 79327
A17: CASH FLOW STATEMENT
A18: USD millions | B18: FY2022 | C18: FY2023 | D18: FY2024 | E18: FY2025
A19: CFO(cash Flow from operations) | B19: 9108 | C19: 5641 | D19: 28090 | E19: 64089
A20: CFI(cash flow from investing activities) | B20: -9830 | C20: 7375 | D20: -10566 | E20: -20421
A21: CFF(cash flow from financing activities) | B21: 1865 | C21: -11617 | D21: -13633 | E21: -42359
A22: Net Change Cash | B22: 1143 | C22: 1399 | D22: 3891 | E22: 1309

Sheet RawFin_ARM
A1: INCOME STATEMENT
A2: USD millions | B2: FY2023 | C2: FY2024 | D2: FY2025
A3: Revenue | B3: 2670 | C3: 3227 | D3: 4007
A4: Cost of revenue | B4: 149 | C4: 189 | D4: 123
A5: Gross Profit | B5: 2521 | C5: 3038 | D5: 3884
A6: Operating Exp | B6: 2131 | C6: 2857 | D6: 3076
A7: EBIT(Operating profit) | B7: 390 | C7: 181 | D7: 808
A8: Net Income | B8: 316 | C8: 196 | D8: 653
A10: BALANCE SHEET
A11: USD millions | B11: FY2023 | C11: FY2024 | D11: FY2025
A12: Cash | B12: 1447 | C12: 1925 | D12: 2089
A13: Total Assets | B13: 4584 | C13: 8051 | D13: 9140
A14: Total Liabilities | B14: 2554 | C14: 2775 | D14: 2325
A15: Total Equity | B15: 2030 | C15: 5276 | D15: 6815
A17: CASH FLOW STATEMENT
A18: USD millions | B18: FY2023 | C18: FY2024 | D18: FY2025
A19: CFO(cash Flow from operations) | B19: N/A | C19: 833 | D19: 179
A20: CFI(cash flow from investing activities) | B20: N/A | C20: -422 | D20: 43
A21: CFF(cash flow from financing activities) | B21: N/A | C21: -45 | D21: -60
A22: Net Change Cash | B22: N/A | C22: 366 | D22: 162

Sheet DCF_ARM
A1: A) Revenue Forecast Section
A2: Year | B2: FY2025A | C2: FY2026E | D2: FY2027E | E2: FY2028E | F2: FY2029E | G2: FY2030E
A3: Revenue | B3: 4007 | C3: 4808 | D3: 5673 | E3: 6579 | F3: 7505 | G3: 8405
A4: YoY Growth % | C4: 0.2 | D4: 0.18 | E4: 0.16 | F4: 0.14 | G4: 0.12
A6: B) Operating Line Items
B7: FY2025A | C7: FY2026E | D7: FY2027E | E7: FY2028E | F7: FY2029E | G7: FY2030E
A8: Cost of Sales (% of revenue) | B8: 0.03 | C8: 0.03 | D8: 0.03 | E8: 0.03 | F8: 0.03 | G8: 0.03
A9: R&D (% of revenue) | B9: 0.523 | C9: 0.51 | D9: 0.5 | E9: 0.48 | F9: 0.47 | G9: 0.46
A10: SG&A (% of revenue) | B10: 0.244 | C10: 0.24 | D10: 0.23 | E10: 0.22 | F10: 0.21 | G10: 0.2
A11: Operating Profit (EBIT) | B11: 808 | C11: =C3*(1-(C8+C9+C10)) -> 1057.76 | D11: =D3*(1-(D8+D9+D10)) -> 1361.52 | E11: =E3*(1-(E8+E9+E10)) -> 1776.33 | F11: =F3*(1-(F8+F9+F10)) -> 2176.45 | G11: =G3*(1-(G8+G9+G10)) -> 2605.55
A15: C) Tax, NOPAT
B16: FY2025A | C16: FY2026E | D16: FY2027E | E16: FY2028E | F16: FY2029E | G16: FY2030E
A17: EBIT | B17: 808 | C17: =C3*(1-(C8+C9+C10)) -> 1057.76 | D17: =D3*(1-(D8+D9+D10)) -> 1361.52 | E17: =E3*(1-(E8+E9+E10)) -> 1776.33 | F17: =F3*(1-(F8+F9+F10)) -> 2176.45 | G17: =G3*(1-(G8+G9+G10)) -> 2605.55
A18: Tax Rate | B18: 0.14 | C18: 0.14 | D18: 0.14 | E18: 0.14 | F18: 0.14 | G18: 0.14
A19: NOPAT | B19: =(B17*(1-B18)) -> 694.88 | C19: =(C17*(1-C18)) -> 909.6736 | D19: =(D17*(1-D18)) -> 1170.9072 | E19: =(E17*(1-E18)) -> 1527.6438 | F19: =(F17*(1-F18)) -> 1871.747 | G19: =(G17*(1-G18)) -> 2240.773
A21: D) Free Cash Flow (FCF)
B22: FY2025A | C22: FY2026E | D22: FY2027E | E22: FY2028E | F22: FY2029E | G22: FY2030E
A23: Depreciation & Amortization | B23: =B3*3% -> 120.21 | C23: =C3*3% -> 144.24 | D23: =D3*3% -> 170.19 | E23: =E3*3% -> 197.37 | F23: =F3*3% -> 225.15 | G23: =G3*3% -> 252.15
A24: CapEx | B24: =-(B3*2.5%) -> -100.175 | C24: =-(C3*2.5%) -> -120.2 | D24: =-(D3*2.5%) -> -141.825 | E24: =-(E3*2.5%) -> -164.475 | F24: =-(F3*2.5%) -> -187.625 | G24: =-(G3*2.5%) -> -210.125
A25: Change in Working Capital | B25: =-(B3*1%) -> -40.07 | C25: =-(C3*1%) -> -48.08 | D25: =-(D3*1%) -> -56.73 | E25: =-(E3*1%) -> -65.79 | F25: =-(F3*1%) -> -75.05 | G25: =-(G3*1%) -> -84.05
A26: Free Cash Flow (FCF) | B26: =B19+B23+B24+B25 -> 674.845 | C26: =C19+C23+C24+C25 -> 885.6336 | D26: =D19+D23+D24+D25 -> 1142.5422 | E26: =E19+E23+E24+E25 -> 1494.7488 | F26: =F19+F23+F24+F25 -> 1834.222 | G26: =G19+G23+G24+G25 -> 2198.748
A27: FCF = NOPAT + Depreciation – CapEx – Change in Working Capital
A28: E) Discounting the Cash Flows
B29: FY2025A | C29: FY2026E | D29: FY2027E | E29: FY2028E | F29: FY2029E | G29: FY2030E
A30: WACC (Weighted Average Cost of Capital) | B30: 0.1
A31: Terminal Growth Rate(g) | B31: 0.03
A32: Terminal Value | G32: =G26*((1+B31)/(B30-B31)) -> 32353.006
A33: Discount Factor | C33: =1/(1+B30)^1 -> 0.90909091 | D33: =1/(1+B30)^2 -> 0.82644628 | E33: =1/(1+B30)^3 -> 0.7513148 | F33: =1/(1+B30)^4 -> 0.68301346 | G33: =1/(1+B30)^5 -> 0.62092132
A34: PV of FCF | C34: =C26*C33 -> 805.12145 | D34: =D26*D33 -> 944.24975 | E34: =E26*E33 -> 1123.0269 | F34: =F26*F33 -> 1252.7983 | G34: =G26*G33 -> 1365.2495
A35: PV of Terminal Value | G35: =G32*G33 -> 20088.671
A36: Total Enterprise Value (EV) | B36: =SUM(C34:G34)+G35 -> 25579.117

Sheet BULL_DCF
A1: A) Revenue Forecast Section(BULL GROWTH)
A2: Year | B2: FY2025A | C2: FY2026E | D2: FY2027E | E2: FY2028E | F2: FY2029E | G2: FY2030E
A3: Revenue | B3: 4007 | C3: =B3*(1+C4) -> 5008.75 | D3: =C3*(1+D4) -> 6160.7625 | E3: =D3*(1+E4) -> 7392.915 | F3: =E3*(1+F4) -> 8723.6397 | G3: =F3*(1+G4) -> 10119.422
A4: YoY Growth % | C4: 0.25 | D4: 0.23 | E4: 0.2 | F4: 0.18 | G4: 0.16
A6: B) Operating Line Items
B7: FY2025A | C7: FY2026E | D7: FY2027E | E7: FY2028E | F7: FY2029E | G7: FY2030E
A8: Cost of Sales (% of revenue) | B8: 0.03 | C8: 0.028 | D8: 0.028 | E8: 0.028 | F8: 0.028 | G8: 0.028
A9: R&D (% of revenue) | B9: 0.523 | C9: 0.5 | D9: 0.49 | E9: 0.47 | F9: 0.45 | G9: 0.44
A10: SG&A (% of revenue) | B10: 0.244 | C10: 0.22 | D10: 0.21 | E10: 0.2 | F10: 0.19 | G10: 0.18
A11: Operating Profit (EBIT) | B11: 808 | C11: =C3*(1-(C8+C9+C10)) -> 1262.205 | D11: =D3*(1-(D8+D9+D10)) -> 1675.7274 | E11: =E3*(1-(E8+E9+E10)) -> 2232.6603 | F11: =F3*(1-(F8+F9+F10)) -> 2896.2484 | G11: =G3*(1-(G8+G9+G10)) -> 3562.0366
A15: C) Tax, NOPAT
B16: FY2025A | C16: FY2026E | D16: FY2027E | E16: FY2028E | F16: FY2029E | G16: FY2030E
A17: EBIT | B17: 808 | C17: =C3*(1-(C8+C9+C10)) -> 1262.205 | D17: =D3*(1-(D8+D9+D10)) -> 1675.7274 | E17: =E3*(1-(E8+E9+E10)) -> 2232.6603 | F17: =F3*(1-(F8+F9+F10)) -> 2896.2484 | G17: =G3*(1-(G8+G9+G10)) -> 3562.0366
A18: Tax Rate | B18: 0.14 | C18: 0.14 | D18: 0.14 | E18: 0.14 | F18: 0.14 | G18: 0.14
A19: NOPAT | B19: =(B17*(1-B18)) -> 694.88 | C19: =(C17*(1-C18)) -> 1085.4963 | D19: =(D17*(1-D18)) -> 1441.1256 | E19: =(E17*(1-E18)) -> 1920.0879 | F19: =(F17*(1-F18)) -> 2490.7736 | G19: =(G17*(1-G18)) -> 3063.3514
A21: D) Free Cash Flow (FCF)
B22: FY2025A | C22: FY2026E | D22: FY2027E | E22: FY2028E | F22: FY2029E | G22: FY2030E
A23: Depreciation & Amortization | B23: =B3*3% -> 120.21 | C23: =C3*3% -> 150.2625 | D23: =D3*3% -> 184.82287 | E23: =E3*3% -> 221.78745 | F23: =F3*3% -> 261.70919 | G23: =G3*3% -> 303.58266
A24: CapEx | B24: =-(B3*2.5%) -> -100.175 | C24: =-(C3*2.5%) -> -125.21875 | D24: =-(D3*2.5%) -> -154.01906 | E24: =-(E3*2.5%) -> -184.82287 | F24: =-(F3*2.5%) -> -218.09099 | G24: =-(G3*2.5%) -> -252.98555
A25: Change in Working Capital | B25: =-(B3*1%) -> -40.07 | C25: =-(C3*1%) -> -50.0875 | D25: =-(D3*1%) -> -61.607625 | E25: =-(E3*1%) -> -73.92915 | F25: =-(F3*1%) -> -87.236397 | G25: =-(G3*1%) -> -101.19422
A26: Free Cash Flow (FCF) | B26: =B19+B23+B24+B25 -> 674.845 | C26: =C19+C23+C24+C25 -> 1060.4525 | D26: =D19+D23+D24+D25 -> 1410.3218 | E26: =E19+E23+E24+E25 -> 1883.1233 | F26: =F19+F23+F24+F25 -> 2447.1554 | G26: =G19+G23+G24+G25 -> 3012.7543
A27: FCF = NOPAT + Depreciation – CapEx – Change in Working Capital
A28: E) Discounting the Cash Flows
B29: FY2025A | C29: FY2026E | D29: FY2027E | E29: FY2028E | F29: FY2029E | G29: FY2030E
A30: WACC (Weighted Average Cost of Capital) | B30: 0.09
A31: Terminal Growth Rate(g) | B31: 0.035
A32: Terminal Value | G32: =G26*((1+B31)/(B30-B31)) -> 56694.559
A33: Discount Factor | C33: =1/(1+B30)^1 -> 0.91743119 | D33: =1/(1+B30)^2 -> 0.84167999 | E33: =1/(1+B30)^3 -> 0.77218348 | F33: =1/(1+B30)^4 -> 0.70842521 | G33: =1/(1+B30)^5 -> 0.64993139
A34: PV of FCF | C34: =C26*C33 -> 972.89225 | D34: =D26*D33 -> 1187.0396 | E34: =E26*E33 -> 1454.1167 | F34: =F26*F33 -> 1733.6266 | G34: =G26*G33 -> 1958.0836
A35: PV of Terminal Value | G35: =G32*G33 -> 36847.573
A36: Total Enterprise Value (EV) | B36: =SUM(C34:G34)+G35 -> 44153.332

Sheet BEAR_DCF
A1: A) Revenue Forecast Section(BEAR CASE)
A2: Year | B2: FY2025A | C2: FY2026E | D2: FY2027E | E2: FY2028E | F2: FY2029E | G2: FY2030E
A3: Revenue | B3: 4007 | C3: =B3*(1+C4) -> 4487.84 | D3: =C3*(1+D4) -> 4936.624 | E3: =D3*(1+E4) -> 5331.5539 | F3: =E3*(1+F4) -> 5704.7627 | G3: =F3*(1+G4) -> 6047.0485
A4: YoY Growth % | C4: 0.12 | D4: 0.1 | E4: 0.08 | F4: 0.07 | G4: 0.06
A6: B) Operating Line Items
B7: FY2025A | C7: FY2026E | D7: FY2027E | E7: FY2028E | F7: FY2029E | G7: FY2030E
A8: Cost of Sales (% of revenue) | B8: 0.03 | C8: 0.032 | D8: 0.032 | E8: 0.032 | F8: 0.032 | G8: 0.032
A9: R&D (% of revenue) | B9: 0.523 | C9: 0.52 | D9: 0.52 | E9: 0.51 | F9: 0.5 | G9: 0.49
A10: SG&A (% of revenue) | B10: 0.244 | C10: 0.24 | D10: 0.24 | E10: 0.23 | F10: 0.23 | G10: 0.22
A11: Operating Profit (EBIT) | B11: 808 | C11: =C3*(1-(C8+C9+C10)) -> 933.47072 | D11: =D3*(1-(D8+D9+D10)) -> 1026.8178 | E11: =E3*(1-(E8+E9+E10)) -> 1215.5943 | F11: =F3*(1-(F8+F9+F10)) -> 1357.7335 | G11: =G3*(1-(G8+G9+G10)) -> 1560.1385
A15: C) Tax, NOPAT
B16: FY2025A | C16: FY2026E | D16: FY2027E | E16: FY2028E | F16: FY2029E | G16: FY2030E
A17: EBIT | B17: 808 | C17: =C3*(1-(C8+C9+C10)) -> 933.47072 | D17: =D3*(1-(D8+D9+D10)) -> 1026.8178 | E17: =E3*(1-(E8+E9+E10)) -> 1215.5943 | F17: =F3*(1-(F8+F9+F10)) -> 1357.7335 | G17: =G3*(1-(G8+G9+G10)) -> 1560.1385
A18: Tax Rate | B18: 0.14 | C18: 0.14 | D18: 0.14 | E18: 0.14 | F18: 0.14 | G18: 0.14
A19: NOPAT | B19: =(B17*(1-B18)) -> 694.88 | C19: =(C17*(1-C18)) -> 802.78482 | D19: =(D17*(1-D18)) -> 883.0633 | E19: =(E17*(1-E18)) -> 1045.4111 | F19: =(F17*(1-F18)) -> 1167.6508 | G19: =(G17*(1-G18)) -> 1341.7191
A21: D) Free Cash Flow (FCF)
B22: FY2025A | C22: FY2026E | D22: FY2027E | E22: FY2028E | F22: FY2029E | G22: FY2030E
A23: Depreciation & Amortization | B23: =B3*3% -> 120.21 | C23: =C3*3% -> 134.6352 | D23: =D3*3% -> 148.09872 | E23: =E3*3% -> 159.94662 | F23: =F3*3% -> 171.14288 | G23: =G3*3% -> 181.41145
A24: CapEx | B24: =-(B3*2.5%) -> -100.175 | C24: =-(C3*2.5%) -> -112.196 | D24: =-(D3*2.5%) -> -123.4156 | E24: =-(E3*2.5%) -> -133.28885 | F24: =-(F3*2.5%) -> -142.61907 | G24: =-(G3*2.5%) -> -151.17621
A25: Change in Working Capital | B25: =-(B3*1%) -> -40.07 | C25: =-(C3*1%) -> -44.8784 | D25: =-(D3*1%) -> -49.36624 | E25: =-(E3*1%) -> -53.315539 | F25: =-(F3*1%) -> -57.047627 | G25: =-(G3*1%) -> -60.470485
A26: Free Cash Flow (FCF) | B26: =B19+B23+B24+B25 -> 674.845 | C26: =C19+C23+C24+C25 -> 780.34562 | D26: =D19+D23+D24+D25 -> 858.38018 | E26: =E19+E23+E24+E25 -> 1018.7533 | F26: =F19+F23+F24+F25 -> 1139.127 | G26: =G19+G23+G24+G25 -> 1311.4839
A27: FCF = NOPAT + Depreciation – CapEx – Change in Working Capital
A28: E) Discounting the Cash Flows
B29: FY2025A | C29: FY2026E | D29: FY2027E | E29: FY2028E | F29: FY2029E | G29: FY2030E
A30: WACC (Weighted Average Cost of Capital) | B30: 0.11
A31: Terminal Growth Rate(g) | B31: 0.02
A32: Terminal Value | G32: =G26*((1+B31)/(B30-B31)) -> 14863.484
A33: Discount Factor | C33: =1/(1+B30)^1 -> 0.9009009 | D33: =1/(1+B30)^2 -> 0.81162243 | E33: =1/(1+B30)^3 -> 0.73119138 | F33: =1/(1+B30)^4 -> 0.65873097 | G33: =1/(1+B30)^5 -> 0.59345133
A34: PV of FCF | C34: =C26*C33 -> 703.01407 | D34: =D26*D33 -> 696.68061 | E34: =E26*E33 -> 744.90365 | F34: =F26*F33 -> 750.37825 | G34: =G26*G33 -> 778.30184
A35: PV of Terminal Value | G35: =G32*G33 -> 8820.7542
A36: Total Enterprise Value (EV) | B36: =SUM(C34:G34)+G35 -> 12494.033

Sheet Sensitivity
A1: EV Sensitivity to WACC and Terminal Growth
A2: WACC \ g | B2: 0.02 | C2: 0.025 | D2: 0.03 | E2: 0.035 | F2: 0.04
A3: 0.085 | B3: =(DCF_ARM!C26/(1+A3)^1) + (DCF_ARM!D26/(1+A3)^2) + (DCF_ARM!E26/(1+A3)^3) + (DCF_ARM!F26/(1+A3)^4) + (DCF_ARM!G26/(1+A3)^5) + ( (DCF_ARM!G26*(1+B2)/(A3-B2)) / (1+A3)^5 ) -> 28689.185 | C3: =(DCF_ARM!C26/(1+A3)^1) + (DCF_ARM!D26/(1+A3)^2) + (DCF_ARM!E26/(1+A3)^3) + (DCF_ARM!F26/(1+A3)^4) + (DCF_ARM!G26/(1+A3)^5) + ( (DCF_ARM!G26*(1+C2)/(A3-C2)) / (1+A3)^5 ) -> 30723.236 | D3: =(DCF_ARM!C26/(1+A3)^1) + (DCF_ARM!D26/(1+A3)^2) + (DCF_ARM!E26/(1+A3)^3) + (DCF_ARM!F26/(1+A3)^4) + (DCF_ARM!G26/(1+A3)^5) + ( (DCF_ARM!G26*(1+D2)/(A3-D2)) / (1+A3)^5 ) -> 33127.115 | E3: =(DCF_ARM!C26/(1+A3)^1) + (DCF_ARM!D26/(1+A3)^2) + (DCF_ARM!E26/(1+A3)^3) + (DCF_ARM!F26/(1+A3)^4) + (DCF_ARM!G26/(1+A3)^5) + ( (DCF_ARM!G26*(1+E2)/(A3-E2)) / (1+A3)^5 ) -> 36011.769 | F3: =(DCF_ARM!C26/(1+A3)^1) + (DCF_ARM!D26/(1+A3)^2) + (DCF_ARM!E26/(1+A3)^3) + (DCF_ARM!F26/(1+A3)^4) + (DCF_ARM!G26/(1+A3)^5) + ( (DCF_ARM!G26*(1+F2)/(A3-F2)) / (1+A3)^5 ) -> 39537.458
A4: 0.09 | B4: =(DCF_ARM!C26/(1+A4)^1) + (DCF_ARM!D26/(1+A4)^2) + (DCF_ARM!E26/(1+A4)^3) + (DCF_ARM!F26/(1+A4)^4) + (DCF_ARM!G26/(1+A4)^5) + ( (DCF_ARM!G26*(1+B2)/(A4-B2)) / (1+A4)^5 ) -> 26479.914 | C4: =(DCF_ARM!C26/(1+A4)^1) + (DCF_ARM!D26/(1+A4)^2) + (DCF_ARM!E26/(1+A4)^3) + (DCF_ARM!F26/(1+A4)^4) + (DCF_ARM!G26/(1+A4)^5) + ( (DCF_ARM!G26*(1+C2)/(A4-C2)) / (1+A4)^5 ) -> 28191.616 | D4: =(DCF_ARM!C26/(1+A4)^1) + (DCF_ARM!D26/(1+A4)^2) + (DCF_ARM!E26/(1+A4)^3) + (DCF_ARM!F26/(1+A4)^4) + (DCF_ARM!G26/(1+A4)^5) + ( (DCF_ARM!G26*(1+D2)/(A4-D2)) / (1+A4)^5 ) -> 30188.601 | E4: 32548.69 | F4: 35380.79
A5: 0.1 | B5: =(DCF_ARM!C26/(1+A5)^1) + (DCF_ARM!D26/(1+A5)^2) + (DCF_ARM!E26/(1+A5)^3) + (DCF_ARM!F26/(1+A5)^4) + (DCF_ARM!G26/(1+A5)^5) + ( (DCF_ARM!G26*(1+B2)/(A5-B2)) / (1+A5)^5 ) -> 22897.377 | C5: =(DCF_ARM!C26/(1+A5)^1) + (DCF_ARM!D26/(1+A5)^2) + (DCF_ARM!E26/(1+A5)^3) + (DCF_ARM!F26/(1+A5)^4) + (DCF_ARM!G26/(1+A5)^5) + ( (DCF_ARM!G26*(1+C2)/(A5-C2)) / (1+A5)^5 ) -> 24148.856 | D5: =(DCF_ARM!C26/(1+A5)^1) + (DCF_ARM!D26/(1+A5)^2) + (DCF_ARM!E26/(1+A5)^3) + (DCF_ARM!F26/(1+A5)^4) + (DCF_ARM!G26/(1+A5)^5) + ( (DCF_ARM!G26*(1+D2)/(A5-D2)) / (1+A5)^5 ) -> 25579.117 | E5: 28722.943 | F5: 29154.79
A6: 0.11 | B6: =(DCF_ARM!C26/(1+A6)^1) + (DCF_ARM!D26/(1+A6)^2) + (DCF_ARM!E26/(1+A6)^3) + (DCF_ARM!F26/(1+A6)^4) + (DCF_ARM!G26/(1+A6)^5) + ( (DCF_ARM!G26*(1+B2)/(A6-B2)) / (1+A6)^5 ) -> 20119.536 | C6: 21066.2 | D6: 22131.19 | E6: 23338.18 | F6: 24717.59
A7: 0.12 | B7: =(DCF_ARM!C26/(1+A7)^1) + (DCF_ARM!D26/(1+A7)^2) + (DCF_ARM!E26/(1+A7)^3) + (DCF_ARM!F26/(1+A7)^4) + (DCF_ARM!G26/(1+A7)^5) + ( (DCF_ARM!G26*(1+B2)/(A7-B2)) / (1+A7)^5 ) -> 17904.627 | C7: 18640.08 | D7: 19457.24 | E7: 20370.54 | F7: 21397.99
A9: Enterprise Value Semstivity to Revenue Growth & EBIT Margin
A10: Rev Growth \ EBIT | B10: 0.25 | C10: 0.27 | D10: 0.29 | E10: 0.31 | F10: 0.33
A11: 0.12 | B11: 24434.42 | C11: 24935.58 | D11: 25445.28 | E11: 25963.63 | F11: 26490.74
A12: 0.14 | B12: 24935.58 | C12: 25446.16 | D12: 25965.29 | E12: 26493.08 | F12: 27029.64
A13: 0.16 | B13: 25445.28 | C13: 25965.29 | D13: 26493.08 | E13: 27028.94 | F13: 27572.87
A14: 0.18 | B14: 25963.63 | C14: 26493.08 | D14: 27028.94 | E14: 27572.87 | F14: 28124.88
A15: 0.2 | B15: 26490.74 | C15: 27029.64 | D15: 27572.87 | E15: 28124.88 | F15: 28684.87

Sheet Charts
A1: ARM Revenue Forecast (USD millions)
A2: Year | B2: Base | C2: Bull | D2: Bear
A3: 2025 | B3: 4007 | C3: 4007 | D3: 4007
A4: 2026 | B4: 4808 | C4: 5009 | D4: 4488
A5: 2027 | B5: 5673 | C5: 6161 | D5: 4937
A6: 2028 | B6: 6579 | C6: 7393 | D6: 5332
A7: 2029 | B7: 7505 | C7: 8724 | D7: 5705
A8: 2030 | B8: 8405 | C8: 10119 | D8: 6047
A10: Free Cash Flow Forecast (USD millions)
A11: Year | B11: Base | C11: Bull | D11: Bear
A12: 2025 | B12: 674.85 | C12: 674.85 | D12: 674.85
A13: 2026 | B13: 885.63 | C13: 1060.45 | D13: 780.35
A14: 2027 | B14: 1142.54 | C14: 1410.32 | D14: 858.38
A15: 2028 | B15: 1494.75 | C15: 1883.12 | D15: 1018.75
A16: 2029 | B16: 1834.22 | C16: 2447.16 | D16: 1139.13
A17: 2030 | B17: 2198.75 | C17: 3012.75 | D17: 1311.48
A19: Enterprise value composition (Base)
A20: Company | B20: Value
A21: PV of Explicit FCFs | B21: 5490.47
A22: PV of Terminal value | B22: 20088.67
A24: EBIT Margin Expansion
A25: Year | B25: Base | C25: Bull | D25: Bear
A26: 2025 | B26: 0.2016 | C26: 0.2016 | D26: 0.2016
A27: 2026 | B27: 0.2199 | C27: 0.252 | D27: 0.208
A28: 2027 | B28: 0.24 | C28: 0.272 | D28: 0.208
A29: 2028 | B29: 0.27 | C29: 0.302 | D29: 0.228
A30: 2029 | B30: 0.29 | C30: 0.332 | D30: 0.238
A31: 2030 | B31: 0.31 | C31: 0.352 | D31: 0.258
